Metadata-Version: 2.1
Name: cryolo
Version: 1.9.4
Summary: Picking procedure for cryo em single particle analysis
Home-page: https://cryolo.readthedocs.io/en/stable/index.html
Author: Thorsten Wagner
Author-email: thorsten.wagner@mpi-dortmund.mpg.de
License: Other/Proprietary License (all rights reserved)
Classifier: Development Status :: 5 - Production/Stable
Classifier: Environment :: Console
Classifier: Environment :: X11 Applications
Classifier: Intended Audience :: End Users/Desktop
Classifier: Topic :: Scientific/Engineering :: Artificial Intelligence
Classifier: Topic :: Scientific/Engineering :: Bio-Informatics
Classifier: Programming Language :: Python :: 3
Classifier: License :: Other/Proprietary License
Requires-Python: >=3.5.0, <3.9
Provides-Extra: gpu
Provides-Extra: cpu
Provides-Extra: c11
License-File: LICENSE
